Workbook

Sheet Inputs
A1: Parameter | B1: Value | C1: Unit / Note
A2: Starting live weight | B2: 200 | C2: kg
A3: Purchase price | B3: 80000 | C3: BDT
A4: Current meat price | B4: 680 | C4: BDT/kg
A5: Initial meat yield | B5: 0.5 | C5: 50% of live weight
A6: Daily live-weight gain | B6: 0.7 | C6: kg/day
A7: Meat yield on daily gain | B7: 0.5 | C7: 0.35 kg meat from 0.70 kg live gain
A8: Daily feed quantity | B8: 3 | C8: kg/day
A9: Feed price | B9: 44.3 | C9: BDT/kg
A10: Daily grass cost | B10: 20 | C10: BDT/day
A11: Daily other cost | B11: 30 | C11: BDT/day
A12: Monthly labor cost | B12: 1500 | C12: BDT/month
A13: Fattening period | B13: 120 | C13: days

Sheet Daily Projection
A1: Day | B1: Live Weight (kg) | C1: Meat Weight (kg) | D1: Feed Qty (kg) | E1: Feed Cost (BDT) | F1: Grass Cost | G1: Other Cost | H1: Labor Cost | I1: Daily Total Cost | J1: Meat Gain (kg) | K1: Meat Value (BDT) | L1: Cumulative Cost | M1: Total Investment | N1: Profit / Loss | O1: Profit %
A2: 1 | B2: =Inputs!$B$2+Inputs!$B$6*A2 -> 200.70 | C2: =B2*Inputs!$B$5 -> 100.35 | D2: =Inputs!$B$8*(B2/Inputs!$B$2) -> 3.01 | E2: =D2*Inputs!$B$9 -> 133.37 | F2: =Inputs!$B$10 -> 20.00 | G2: =Inputs!$B$11 -> 30.00 | H2: =Inputs!$B$12/30 -> 50.00 | I2: =SUM(E2:H2) -> 233.37 | J2: =Inputs!$B$6*Inputs!$B$7 -> 0.35 | K2: =C2*Inputs!$B$4 -> 68,238.00 | L2: =SUM($I$2:I2) -> 233.37 | M2: =Inputs!$B$3+L2 -> 80,233.37 | N2: =K2-M2 -> -11,995.37 | O2: =IF(M2=0,0,N2/M2) -> -14.95%
A3: 2 | B3: =Inputs!$B$2+Inputs!$B$6*A3 -> 201.40 | C3: =B3*Inputs!$B$5 -> 100.70 | D3: =Inputs!$B$8*(B3/Inputs!$B$2) -> 3.02 | E3: =D3*Inputs!$B$9 -> 133.83 | F3: =Inputs!$B$10 -> 20.00 | G3: =Inputs!$B$11 -> 30.00 | H3: =Inputs!$B$12/30 -> 50.00 | I3: =SUM(E3:H3) -> 233.83 | J3: =Inputs!$B$6*Inputs!$B$7 -> 0.35 | K3: =C3*Inputs!$B$4 -> 68,476.00 | L3: =SUM($I$2:I3) -> 467.20 | M3: =Inputs!$B$3+L3 -> 80,467.20 | N3: =K3-M3 -> -11,991.20 | O3: =IF(M3=0,0,N3/M3) -> -14.90%
A4: 3 | B4: =Inputs!$B$2+Inputs!$B$6*A4 -> 202.10 | C4: =B4*Inputs!$B$5 -> 101.05 | D4: =Inputs!$B$8*(B4/Inputs!$B$2) -> 3.03 | E4: =D4*Inputs!$B$9 -> 134.30 | F4: =Inputs!$B$10 -> 20.00 | G4: =Inputs!$B$11 -> 30.00 | H4: =Inputs!$B$12/30 -> 50.00 | I4: =SUM(E4:H4) -> 234.30 | J4: =Inputs!$B$6*Inputs!$B$7 -> 0.35 | K4: =C4*Inputs!$B$4 -> 68,714.00 | L4: =SUM($I$2:I4) -> 701.49 | M4: =Inputs!$B$3+L4 -> 80,701.49 | N4: =K4-M4 -> -11,987.49 | O4: =IF(M4=0,0,N4/M4) -> -14.85%
A5: 4 | B5: =Inputs!$B$2+Inputs!$B$6*A5 -> 202.80 | C5: =B5*Inputs!$B$5 -> 101.40 | D5: =Inputs!$B$8*(B5/Inputs!$B$2) -> 3.04 | E5: =D5*Inputs!$B$9 -> 134.76 | F5: =Inputs!$B$10 -> 20.00 | G5: =Inputs!$B$11 -> 30.00 | H5: =Inputs!$B$12/30 -> 50.00 | I5: =SUM(E5:H5) -> 234.76 | J5: =Inputs!$B$6*Inputs!$B$7 -> 0.35 | K5: =C5*Inputs!$B$4 -> 68,952.00 | L5: =SUM($I$2:I5) -> 936.25 | M5: =Inputs!$B$3+L5 -> 80,936.25 | N5: =K5-M5 -> -11,984.25 | O5: =IF(M5=0,0,N5/M5) -> -14.81%
A6: 5 | B6: =Inputs!$B$2+Inputs!$B$6*A6 -> 203.50 | C6: =B6*Inputs!$B$5 -> 101.75 | D6: =Inputs!$B$8*(B6/Inputs!$B$2) -> 3.05 | E6: =D6*Inputs!$B$9 -> 135.23 | F6: =Inputs!$B$10 -> 20.00 | G6: =Inputs!$B$11 -> 30.00 | H6: =Inputs!$B$12/30 -> 50.00 | I6: =SUM(E6:H6) -> 235.23 | J6: =Inputs!$B$6*Inputs!$B$7 -> 0.35 | K6: =C6*Inputs!$B$4 -> 69,190.00 | L6: =SUM($I$2:I6) -> 1,171.48 | M6: =Inputs!$B$3+L6 -> 81,171.48 | N6: =K6-M6 -> -11,981.48 | O6: =IF(M6=0,0,N6/M6) -> -14.76%
A7: 6 | B7: =Inputs!$B$2+Inputs!$B$6*A7 -> 204.20 | C7: =B7*Inputs!$B$5 -> 102.10 | D7: =Inputs!$B$8*(B7/Inputs!$B$2) -> 3.06 | E7: =D7*Inputs!$B$9 -> 135.69 | F7: =Inputs!$B$10 -> 20.00 | G7: =Inputs!$B$11 -> 30.00 | H7: =Inputs!$B$12/30 -> 50.00 | I7: =SUM(E7:H7) -> 235.69 | J7: =Inputs!$B$6*Inputs!$B$7 -> 0.35 | K7: =C7*Inputs!$B$4 -> 69,428.00 | L7: =SUM($I$2:I7) -> 1,407.17 | M7: =Inputs!$B$3+L7 -> 81,407.17 | N7: =K7-M7 -> -11,979.17 | O7: =IF(M7=0,0,N7/M7) -> -14.72%
A8: 7 | B8: =Inputs!$B$2+Inputs!$B$6*A8 -> 204.90 | C8: =B8*Inputs!$B$5 -> 102.45 | D8: =Inputs!$B$8*(B8/Inputs!$B$2) -> 3.07 | E8: =D8*Inputs!$B$9 -> 136.16 | F8: =Inputs!$B$10 -> 20.00 | G8: =Inputs!$B$11 -> 30.00 | H8: =Inputs!$B$12/30 -> 50.00 | I8: =SUM(E8:H8) -> 236.16 | J8: =Inputs!$B$6*Inputs!$B$7 -> 0.35 | K8: =C8*Inputs!$B$4 -> 69,666.00 | L8: =SUM($I$2:I8) -> 1,643.32 | M8: =Inputs!$B$3+L8 -> 81,643.32 | N8: =K8-M8 -> -11,977.32 | O8: =IF(M8=0,0,N8/M8) -> -14.67%
A9: 8 | B9: =Inputs!$B$2+Inputs!$B$6*A9 -> 205.60 | C9: =B9*Inputs!$B$5 -> 102.80 | D9: =Inputs!$B$8*(B9/Inputs!$B$2) -> 3.08 | E9: =D9*Inputs!$B$9 -> 136.62 | F9: =Inputs!$B$10 -> 20.00 | G9: =Inputs!$B$11 -> 30.00 | H9: =Inputs!$B$12/30 -> 50.00 | I9: =SUM(E9:H9) -> 236.62 | J9: =Inputs!$B$6*Inputs!$B$7 -> 0.35 | K9: =C9*Inputs!$B$4 -> 69,904.00 | L9: =SUM($I$2:I9) -> 1,879.95 | M9: =Inputs!$B$3+L9 -> 81,879.95 | N9: =K9-M9 -> -11,975.95 | O9: =IF(M9=0,0,N9/M9) -> -14.63%
A10: 9 | B10: =Inputs!$B$2+Inputs!$B$6*A10 -> 206.30 | C10: =B10*Inputs!$B$5 -> 103.15 | D10: =Inputs!$B$8*(B10/Inputs!$B$2) -> 3.09 | E10: =D10*Inputs!$B$9 -> 137.09 | F10: =Inputs!$B$10 -> 20.00 | G10: =Inputs!$B$11 -> 30.00 | H10: =Inputs!$B$12/30 -> 50.00 | I10: =SUM(E10:H10) -> 237.09 | J10: =Inputs!$B$6*Inputs!$B$7 -> 0.35 | K10: =C10*Inputs!$B$4 -> 70,142.00 | L10: =SUM($I$2:I10) -> 2,117.03 | M10: =Inputs!$B$3+L10 -> 82,117.03 | N10: =K10-M10 -> -11,975.03 | O10: =IF(M10=0,0,N10/M10) -> -14.58%
A11: 10 | B11: =Inputs!$B$2+Inputs!$B$6*A11 -> 207.00 | C11: =B11*Inputs!$B$5 -> 103.50 | D11: =Inputs!$B$8*(B11/Inputs!$B$2) -> 3.11 | E11: =D11*Inputs!$B$9 -> 137.55 | F11: =Inputs!$B$10 -> 20.00 | G11: =Inputs!$B$11 -> 30.00 | H11: =Inputs!$B$12/30 -> 50.00 | I11: =SUM(E11:H11) -> 237.55 | J11: =Inputs!$B$6*Inputs!$B$7 -> 0.35 | K11: =C11*Inputs!$B$4 -> 70,380.00 | L11: =SUM($I$2:I11) -> 2,354.58 | M11: =Inputs!$B$3+L11 -> 82,354.58 | N11: =K11-M11 -> -11,974.58 | O11: =IF(M11=0,0,N11/M11) -> -14.54%
A12: 11 | B12: =Inputs!$B$2+Inputs!$B$6*A12 -> 207.70 | C12: =B12*Inputs!$B$5 -> 103.85 | D12: =Inputs!$B$8*(B12/Inputs!$B$2) -> 3.12 | E12: =D12*Inputs!$B$9 -> 138.02 | F12: =Inputs!$B$10 -> 20.00 | G12: =Inputs!$B$11 -> 30.00 | H12: =Inputs!$B$12/30 -> 50.00 | I12: =SUM(E12:H12) -> 238.02 | J12: =Inputs!$B$6*Inputs!$B$7 -> 0.35 | K12: =C12*Inputs!$B$4 -> 70,618.00 | L12: =SUM($I$2:I12) -> 2,592.60 | M12: =Inputs!$B$3+L12 -> 82,592.60 | N12: =K12-M12 -> -11,974.60 | O12: =IF(M12=0,0,N12/M12) -> -14.50%
A13: 12 | B13: =Inputs!$B$2+Inputs!$B$6*A13 -> 208.40 | C13: =B13*Inputs!$B$5 -> 104.20 | D13: =Inputs!$B$8*(B13/Inputs!$B$2) -> 3.13 | E13: =D13*Inputs!$B$9 -> 138.48 | F13: =Inputs!$B$10 -> 20.00 | G13: =Inputs!$B$11 -> 30.00 | H13: =Inputs!$B$12/30 -> 50.00 | I13: =SUM(E13:H13) -> 238.48 | J13: =Inputs!$B$6*Inputs!$B$7 -> 0.35 | K13: =C13*Inputs!$B$4 -> 70,856.00 | L13: =SUM($I$2:I13) -> 2,831.08 | M13: =Inputs!$B$3+L13 -> 82,831.08 | N13: =K13-M13 -> -11,975.08 | O13: =IF(M13=0,0,N13/M13) -> -14.46%
... A121: 120 | B121: =Inputs!$B$2+Inputs!$B$6*A121 -> 284.00 | C121: =B121*Inputs!$B$5 -> 142.00 | D121: =Inputs!$B$8*(B121/Inputs!$B$2) -> 4.26 | E121: =D121*Inputs!$B$9 -> 188.72 | F121: =Inputs!$B$10 -> 20.00 | G121: =Inputs!$B$11 -> 30.00 | H121: =Inputs!$B$12/30 -> 50.00 | I121: =SUM(E121:H121) -> 288.72 | J121: =Inputs!$B$6*Inputs!$B$7 -> 0.35 | K121: =C121*Inputs!$B$4 -> 96,560.00 | L121: =SUM($I$2:I121) -> 31,324.99 | M121: =Inputs!$B$3+L121 -> 111,324.99 | N121: =K121-M121 -> -14,764.99 | O121: =IF(M121=0,0,N121/M121) -> -13.26%

Sheet Summary
A1: Metric | B1: Formula / Result
A2: Starting weight | B2: =Inputs!B2 -> 200.00
A3: Final weight | B3: {=INDEX('Daily Projection'!B:B,Inputs!B13+1)} -> 284.00
A4: Total weight gain | B4: =B3-B2 -> 84.00
A5: Purchase cost | B5: =Inputs!B3 -> 80,000.00
A6: Total feed cost | B6: =SUM('Daily Projection'!E2:E121) -> 19,324.99
A7: Total grass cost | B7: =SUM('Daily Projection'!F2:F121) -> 2,400.00
A8: Total other cost | B8: =SUM('Daily Projection'!G2:G121) -> 3,600.00
A9: Total labor cost | B9: =SUM('Daily Projection'!H2:H121) -> 6,000.00
A10: Total farming cost | B10: =SUM('Daily Projection'!I2:I121) -> 31,324.99
A11: Total investment | B11: =B5+B10 -> 111,324.99
A12: Final meat weight | B12: {=INDEX('Daily Projection'!C:C,Inputs!B13+1)} -> 142.00
A13: Expected sale value | B13: {=INDEX('Daily Projection'!K:K,Inputs!B13+1)} -> 96,560.00
A14: Profit / Loss | B14: =B13-B11 -> -14,764.99
A15: Profit % | B15: =IF(B11=0,0,B14/B11) -> -13.26%
A16: Break-even selling price / live kg | B16: =B11/B3 -> 391.99
A17: Selling price / meat kg used in PDF | B17: =Inputs!B4 -> 680.00
A19: PDF note | B19: The PDF shows 283.3 kg on day 120 and a final value around 96,798 BDT. The clean formula used here is final live weight × 50% meat yield × 680 BDT/kg.
